rsisa/__init__.py
rsisa/annotation_map_split.py
rsisa/ellipse_instance_generation.py
rsisa/evaluation.py
rsisa/instance_registration.py
rsisa/workflow.py
tests/__init__.py
tests/test_annotation_map_split.py
tests/test_ellipse_instance_generation.py
tests/test_evaluation.py
tests/test_instance_registration.py
rsisa-0.1.1.dist-info/LICENSE
rsisa-0.1.1.dist-info/METADATA
rsisa-0.1.1.dist-info/WHEEL
rsisa-0.1.1.dist-info/top_level.txt
rsisa-0.1.1.dist-info/RECORD
