Metadata-Version: 2.1
Name: rsisa
Version: 0.1.1
Summary: Remote Sensing Instance Segmentation Algorithms
Home-page: https://github.com/ZhiangChen/instance_segmentation_remote_sensing
Author: Zhiang Chen
Author-email: zxc251@case.edu
License: UNKNOWN
Platform: UNKNOWN
Classifier: Development Status :: 3 - Alpha
Classifier: Intended Audience :: Developers
Classifier: Programming Language :: Python :: 3
Classifier: Programming Language :: Python :: 3.6
Classifier: Programming Language :: Python :: 3.7
Classifier: Programming Language :: Python :: 3.8
Classifier: License :: OSI Approved :: Apache Software License
Classifier: Operating System :: OS Independent
Requires-Python: >=3.6
Requires-Dist: GDAL (>=3.3.2)
Requires-Dist: fiona (>=1.9.3)
Requires-Dist: geopandas (>=0.12.0)
Requires-Dist: matplotlib (>=3.7.1)
Requires-Dist: numpy (>=1.24.2)
Requires-Dist: opencv-python (>=4.7.0.72)
Requires-Dist: pandas (>=2.0.0)
Requires-Dist: pyproj (>=3.5.0)
Requires-Dist: rasterio (>=1.3.6)
Requires-Dist: rioxarray (>=0.13.4)
Requires-Dist: shapely (>=2.0.1)
Requires-Dist: tqdm (>=4.65.0)
